dotenvhub/__init__.py
dotenvhub/app.py
dotenvhub/cli_parser.py
dotenvhub/config.py
dotenvhub/constants.py
dotenvhub/tui.py
dotenvhub/utils.py
dotenvhub/assets/modal_save.tcss
dotenvhub/assets/modal_shell.tcss
dotenvhub/assets/tui.tcss
dotenvhub/widgets/filepanel.py
dotenvhub/widgets/interactionpanel.py
dotenvhub/widgets/modals.py
dotenvhub/widgets/previewpanel.py
dotenvhub-0.6.1.dist-info/METADATA
dotenvhub-0.6.1.dist-info/WHEEL
dotenvhub-0.6.1.dist-info/entry_points.txt
dotenvhub-0.6.1.dist-info/licenses/LICENSE.txt
dotenvhub-0.6.1.dist-info/RECORD
