Metadata-Version: 2.4
Name: dotenvhub
Version: 0.6.1
Summary: Terminal App to manage .env files written in Python powered by Textual
Project-URL: Repository, https://github.com/Zaloog/dotenvhub
Project-URL: Changelog, https://github.com/Zaloog/dotenvhub/blob/main/CHANGELOG.md
Author-email: Zaloog <gramslars@gmail.com>
License: MIT
License-File: LICENSE.txt
Classifier: Development Status :: 3 - Alpha
Classifier: License :: OSI Approved :: MIT License
Classifier: Operating System :: OS Independent
Classifier: Programming Language :: Python
Classifier: Programming Language :: Python :: 3 :: Only
Classifier: Programming Language :: Python :: 3.10
Classifier: Programming Language :: Python :: 3.11
Classifier: Programming Language :: Python :: 3.12
Classifier: Programming Language :: Python :: 3.13
Requires-Python: >=3.10
Requires-Dist: platformdirs>=4.3.6
Requires-Dist: pyperclip>=1.9.0
Requires-Dist: textual-jumper>=0.2.0
Requires-Dist: textual>=6.0.0
